honeybot/__init__.py
honeybot/__main__.py
honeybot/gui_manager.py
honeybot/lab.py
honeybot/manage.py
honeybot/store.py
honeybot/test_core.py
honeybot/test_legacy_core.py
honeybot/test_plugin_script.py
honeybot/todo.txt
honeybot/api/__init__.py
honeybot/api/commands.py
honeybot/api/generate.py
honeybot/api/init.py
honeybot/api/main.py
honeybot/api/memory.py
honeybot/api/print.py
honeybot/api/utils.py
honeybot/plugins/__init__.py
honeybot/plugins/core/__init__.py
honeybot/plugins/core/joins/__init__.py
honeybot/plugins/core/joins/main.py
honeybot/plugins/core/log/__init__.py
honeybot/plugins/core/log/main.py
honeybot/plugins/core/uptime/__init__.py
honeybot/plugins/core/uptime/main.py
honeybot/plugins/downloaded/__init__.py
honeybot/plugins/downloaded/abbreviation/__init__.py
honeybot/plugins/downloaded/abbreviation/info.py
honeybot/plugins/downloaded/abbreviation/main.py
honeybot/plugins/downloaded/age/__init__.py
honeybot/plugins/downloaded/age/info.py
honeybot/plugins/downloaded/age/main.py
honeybot/plugins/downloaded/anime/__init__.py
honeybot/plugins/downloaded/anime/info.py
honeybot/plugins/downloaded/anime/main.py
honeybot/plugins/downloaded/basketball/__init__.py
honeybot/plugins/downloaded/basketball/info.py
honeybot/plugins/downloaded/basketball/main.py
honeybot/plugins/downloaded/birthparadox/__init__.py
honeybot/plugins/downloaded/birthparadox/info.py
honeybot/plugins/downloaded/birthparadox/main.py
honeybot/plugins/downloaded/bitcoin/__init__.py
honeybot/plugins/downloaded/bitcoin/info.py
honeybot/plugins/downloaded/bitcoin/main.py
honeybot/plugins/downloaded/blackjack/__init__.py
honeybot/plugins/downloaded/blackjack/info.py
honeybot/plugins/downloaded/blackjack/main.py
honeybot/plugins/downloaded/blackjack/poker_assets/__init__.py
honeybot/plugins/downloaded/blackjack/poker_assets/best5.py
honeybot/plugins/downloaded/blackjack/poker_assets/board.py
honeybot/plugins/downloaded/blackjack/poker_assets/card.py
honeybot-6.1.1.dist-info/LICENSE
honeybot-6.1.1.dist-info/METADATA
honeybot-6.1.1.dist-info/WHEEL
honeybot-6.1.1.dist-info/entry_points.txt
honeybot-6.1.1.dist-info/top_level.txt
honeybot-6.1.1.dist-info/RECORD
