Metadata-Version: 2.1
Name: honeybot
Version: 6.1.1
Summary: IRC bot with vast collection of plugins. First timers friendly
Home-page: https://github.com/pyhoneybot/honeybot
Author: Abdur-Rahmaan Janhnageer
Author-email: arj.python@gmail.com
License: MIT
Project-URL: Changelog, https://github.com/pyhoneybot/honeybot/blob/main/CHANGES.md
Keywords: irc bot plugins
Classifier: Development Status :: 4 - Beta
Classifier: Environment :: Console
Classifier: Intended Audience :: Developers
Classifier: License :: OSI Approved :: MIT License
Classifier: Operating System :: OS Independent
Classifier: Programming Language :: Python
Classifier: Programming Language :: Python :: 3.7
Classifier: Programming Language :: Python :: 3.8
Classifier: Programming Language :: Python :: 3.9
Classifier: Programming Language :: Python :: 3.10
Classifier: Programming Language :: Python :: 3.11
Classifier: Programming Language :: Python :: 3 :: Only
Classifier: Topic :: Software Development :: Libraries :: Python Modules
Requires-Python: >=3.7.0
License-File: LICENSE
Requires-Dist: tomli>=2.0.0
